risk_engine/__init__.py
risk_engine/adapters/__init__.py
risk_engine/adapters/freqtrade.py
risk_engine/adapters/generic.py
risk_engine/core/__init__.py
risk_engine/core/config.py
risk_engine/core/engine.py
risk_engine/core/state.py
risk_engine/examples/__init__.py
risk_engine/examples/freqtrade_example.py
risk_engine/guards/__init__.py
risk_engine/guards/drawdown.py
risk_engine/guards/exposure.py
risk_engine/guards/leverage.py
risk_engine/interfaces/__init__.py
risk_engine/interfaces/account.py
risk_engine/interfaces/clock.py
risk_engine/interfaces/position.py
risk_engine/sizing/__init__.py
risk_engine/sizing/fixed_risk.py
risk_engine/sizing/volatility.py
trading_risk_engine-1.0.0.dist-info/licenses/LICENSE
trading_risk_engine-1.0.0.dist-info/METADATA
trading_risk_engine-1.0.0.dist-info/WHEEL
trading_risk_engine-1.0.0.dist-info/top_level.txt
trading_risk_engine-1.0.0.dist-info/RECORD
