Metadata-Version: 2.4
Name: trading-risk-engine
Version: 1.0.0
Summary: Kill-switch and risk control engine for live trading bots
Author: Risk Engine Team
License-Expression: LicenseRef-Commercial
Project-URL: Homepage, https://github.com/yourname/risk-engine
Project-URL: Documentation, https://github.com/yourname/risk-engine#readme
Project-URL: Repository, https://github.com/yourname/risk-engine.git
Keywords: trading,risk-management,algo-trading,freqtrade,kill-switch,position-sizing,drawdown
Classifier: Development Status :: 4 - Beta
Classifier: Intended Audience :: Developers
Classifier: Intended Audience :: Financial and Insurance Industry
Classifier: Operating System :: OS Independent
Classifier: Programming Language :: Python :: 3
Classifier: Programming Language :: Python :: 3.10
Classifier: Programming Language :: Python :: 3.11
Classifier: Programming Language :: Python :: 3.12
Classifier: Topic :: Office/Business :: Financial :: Investment
Classifier: Typing :: Typed
Requires-Python: >=3.10
License-File: LICENSE
Provides-Extra: dev
Requires-Dist: pytest>=7.0.0; extra == "dev"
Requires-Dist: pytest-cov>=4.0.0; extra == "dev"
Dynamic: license-file
